{
  "packageDirectories": [
    {
      "path": "force-app",
      "default": true
    },
    {
      "path": "src/packaged",
      "package": "Orb Developer Demo Package",
      "definitionFile": "config/default-scratch-def.json",
      "versionName": "Package Version Name",
      "versionNumber": "0.1.1.NEXT",
      "default": false
    }
  ],
  "namespace": "",
  "sfdcLoginUrl": "https://curious-impala-bhgtyu-dev-ed.my.salesforce.com",
  "sourceApiVersion": "53.0",
  "packageAliases": {
    "Orb Developer Demo Package": "0Ho7Q000000CaVYSA0"
  }
}
